bin/__init__.py
bin/get_hostname_ip.py
tay_ping/__init__.py
tay_ping/get_hostname_ip.py
tay_ping-0.0.4.dist-info/LICENSE
tay_ping-0.0.4.dist-info/METADATA
tay_ping-0.0.4.dist-info/WHEEL
tay_ping-0.0.4.dist-info/top_level.txt
tay_ping-0.0.4.dist-info/RECORD
