Metadata-Version: 2.1
Name: tay-ping
Version: 0.0.4
Summary: Tay的一个简单测试
Home-page: https://gitee.com/tay3223/bao2.git
Author: 蛋小挞
Author-email: tay3223@qq.com
License: UNKNOWN
Platform: UNKNOWN
Classifier: Programming Language :: Python :: 3
Classifier: License :: OSI Approved :: MIT License
Classifier: Operating System :: OS Independent
Requires-Python: >=3.6
